odoo10_addon_mass_mailing_unique-10.0.1.0.1-py3.8-nspkg.pth
odoo/addons/mass_mailing_unique/README.rst
odoo/addons/mass_mailing_unique/__init__.py
odoo/addons/mass_mailing_unique/__manifest__.py
odoo/addons/mass_mailing_unique/hooks.py
odoo/addons/mass_mailing_unique/i18n/ca.po
odoo/addons/mass_mailing_unique/i18n/de.po
odoo/addons/mass_mailing_unique/i18n/es.po
odoo/addons/mass_mailing_unique/i18n/fr.po
odoo/addons/mass_mailing_unique/i18n/hr.po
odoo/addons/mass_mailing_unique/i18n/it.po
odoo/addons/mass_mailing_unique/i18n/mass_mailing_unique.pot
odoo/addons/mass_mailing_unique/i18n/pt.po
odoo/addons/mass_mailing_unique/i18n/sl.po
odoo/addons/mass_mailing_unique/images/error-duplicated-email.png
odoo/addons/mass_mailing_unique/images/error-duplicated-list.png
odoo/addons/mass_mailing_unique/models/__init__.py
odoo/addons/mass_mailing_unique/models/mass_mailing.py
odoo/addons/mass_mailing_unique/static/description/icon.png
odoo/addons/mass_mailing_unique/tests/__init__.py
odoo/addons/mass_mailing_unique/tests/test_mass_mailing_unique.py
odoo10_addon_mass_mailing_unique-10.0.1.0.1.dist-info/METADATA
odoo10_addon_mass_mailing_unique-10.0.1.0.1.dist-info/WHEEL
odoo10_addon_mass_mailing_unique-10.0.1.0.1.dist-info/namespace_packages.txt
odoo10_addon_mass_mailing_unique-10.0.1.0.1.dist-info/top_level.txt
odoo10_addon_mass_mailing_unique-10.0.1.0.1.dist-info/RECORD
